LICENSE
MANIFEST.in
README.md
requirements.txt
setup.cfg
setup.py
tests/test_config_management.py
tests/test_dot11map.py
tests/test_macvendordb.py
trackerjacker/__init__.py
trackerjacker/__main__.py
trackerjacker/common.py
trackerjacker/config_management.py
trackerjacker/dot11_frame.py
trackerjacker/dot11_mapper.py
trackerjacker/dot11_tracker.py
trackerjacker/ieee_mac_vendor_db.py
trackerjacker/linux_device_management.py
trackerjacker/macos_device_management.py
trackerjacker/oui.txt
trackerjacker/plugin_parser.py
trackerjacker/version.py
trackerjacker.egg-info/PKG-INFO
trackerjacker.egg-info/SOURCES.txt
trackerjacker.egg-info/dependency_links.txt
trackerjacker.egg-info/entry_points.txt
trackerjacker.egg-info/requires.txt
trackerjacker.egg-info/top_level.txt
trackerjacker/plugins/__init__.py
trackerjacker/plugins/foxhunt.py